fluidreleaser/__init__.py
fluidreleaser/__main__.py
fluidreleaser/main.py
fluidreleaser/utils/artifact.py
fluidreleaser/utils/data.py
fluidreleaser/utils/upload.py
fluidreleaser-1.2.0.dist-info/WHEEL
fluidreleaser-1.2.0.dist-info/METADATA
fluidreleaser-1.2.0.dist-info/RECORD
